{
  "select_language": {
    "en": "Please select a language:",
    "ua": "Будь ласка, виберіть мову:",
    "ru": "Пожалуйста, выберите язык:",
    "by": "Калі ласка, выберыце мову:"
  },
  "start_message": {
    "en": "Hello! I’m a crypto monitoring bot.",
    "ua": "Привіт! Я бот для моніторингу криптовалют.",
    "ru": "Привет! Я бот для мониторинга криптовалют.",
    "by": "Прывітанне! Я бот для маніторынгу криптавалют."
  },
  "menu_main": {
    "en": "📋 Main Menu",
    "ua": "📋 Головне Меню",
    "ru": "📋 Главное Меню",
    "by": "📋 Галоўнае Меню"
  },
  "menu_buttons": {
    "price": {
      "en": "💰 Price",
      "ua": "💰 Ціна",
      "ru": "💰 Цена",
      "by": "💰 Кошт"
    },
    "settings": {
      "en": "⚙️ Setting",
      "ua": "⚙️ Налаштування",
      "ru": "⚙️ Настройки",
      "by": "⚙️ Налады"
    },
    "help": {
      "en": "❓ Help",
      "ua": "❓ Допомога",
      "ru": "❓ Помощь",
      "by": "❓ Дапамога"
    }
  },
  "enter_coin": {
    "en": "Enter coin (e.g., BTC):",
    "ua": "Введіть монету (наприклад: BTC):",
    "ru": "Введите монету (например: BTC):",
    "by": "Увядзіце манету (напрыклад: BTC):"
  },
  "coin_not_found": {
    "en": "Coin not found 😔",
    "ua": "Монету не знайдено 😔",
    "ru": "Монета не найдена 😔",
    "by": "Манета не знойдзена 😔"
  },
  "coin_price": {
    "en": "Current price of {coin}: ${price}",
    "ua": "Поточна ціна {coin}: ${price}",
    "ru": "Текущая цена {coin}: ${price}",
    "by": "Бягучы кошт {coin}: ${price}"
  },
  "vip_features": {
    "en": "🔓 VIP gives access to:\n- Price forecast\n- Chart\nGo to [⚙️ Setting > Subscribe] to upgrade",
    "ua": "🔓 У VIP підписці доступні:\n- Прогноз ціни\n- Графік динаміки\nПерейдіть у [⚙️ Setting > Subscribe] для апгрейду",
    "ru": "🔓 В VIP подписке доступны:\n- Прогноз цены\n- График динамики\nПерейдите в [⚙️ Setting > Subscribe] для апгрейда",
    "by": "🔓 У VIP-падпісцы даступна:\n- Прагноз цэны\n- Графік\nПерайдзіце ў [⚙️ Налады > Subscribe], каб абнавіцца"
  },
  "monitoring_input": {
    "free": {
      "en": "Enter up to 3 coins to monitor (comma-separated):",
      "ua": "Введіть до 3 монет для моніторингу (через кому):",
      "ru": "Введите до 3 монет для мониторинга (через запятую):",
      "by": "Увядзіце да 3 манет (праз коску):"
    },
    "vip": {
      "en": "Enter up to 10 coins to monitor (comma-separated):",
      "ua": "Введіть до 10 монет для моніторингу (через кому):",
      "ru": "Введите до 10 монет для мониторинга (через запятую):",
      "by": "Увядзіце да 10 манет (праз коску):"
    }
  },
  "monitoring_confirm": {
    "en": "Now I’m monitoring: {coins}",
    "ua": "Тепер я слідкую за: {coins}",
    "ru": "Теперь я слежу за: {coins}",
    "by": "Цяпер я сачу за: {coins}"
  },
  "subscribe_free": {
    "en": "You’re using the free version.\nUpgrade to VIP to get:\n✅ Up to 10 coins\n✅ Graphs\n✅ Forecasts\n✅ Up to 10 alerts\n[💎 Get VIP]",
    "ua": "У вас безкоштовна версія.\nПридбайте VIP, щоб отримати:\n✅ до 10 монет\n✅ графіки\n✅ прогнози\n✅ до 10 тригерів падіння\n[💎 Придбати VIP]",
    "ru": "У вас бесплатная версия.\nКупите VIP, чтобы получить:\n✅ до 10 монет\n✅ графики\n✅ прогнозы\n✅ до 10 триггеров падения\n[💎 Купить VIP]",
    "by": "Вы карыстаецеся бясплатнай версіяй.\nКупіце VIP:\n✅ да 10 манет\n✅ графікі\n✅ прагнозы\n✅ да 10 трыгераў\n[💎 Набыць VIP]"
  },
  "subscribe_vip": {
    "en": "You have an active VIP subscription.\n[❌ Cancel Subscription]",
    "ua": "У вас активна VIP-підписка.\n[❌ Скасувати підписку]",
    "ru": "У вас активная VIP-подписка.\n[❌ Отменить подписку]",
    "by": "У вас актыўная VIP-падпіска.\n[❌ Скасаваць падпіску]"
  },
  "help_text": {
    "en": "I’m a bot for monitoring cryptocurrency prices.\nFeatures:\n💰 Price check\n📈 Monitor selected coins\n📉 Alert for drop/growth\n🌐 Multilanguage\n🔐 Admin access with 2FA\nFree: 3 coins, 1 trigger\nVIP: 10 coins, charts, forecasts, 10 triggers",
    "ua": "Я бот для моніторингу криптовалютних курсів.\nМої можливості:\n💰 Перевірка ціни\n📈 Моніторинг монет\n📉 Сповіщення про падіння\n🌐 Багатомовний інтерфейс\n🔐 Доступ з 2FA\nFree: 3 монети, 1 тригер\nVIP: 10 монет, графіки, прогнози, 10 тригерів",
    "ru": "Я бот для мониторинга курсов криптовалют.\nВозможности:\n💰 Проверка цены\n📈 Мониторинг монет\n📉 Оповещения о падении\n🌐 Мультиязычный интерфейс\n🔐 Доступ с 2FA\nFree: 3 монеты, 1 триггер\nVIP: 10 монет, графики, прогнозы, 10 триггеров",
    "by": "Я бот для маніторынгу криптавалютных курсаў.\nМае функцыі:\n💰 Праверка цэны\n📈 Маніторынг манет\n📉 Паведамленне пра падзенне\n🌐 Шматмоўны інтэрфейс\n🔐 Доступ з 2FA\nFree: 3 манеты, 1 трыгер\nVIP: 10 манет, графікі, прагнозы, 10 трыгераў"
  }
}
